README.txt
setup.py
docs/HISTORY.txt
docs/INSTALL.txt
docs/LICENSE.GPL
docs/LICENSE.txt
xm/__init__.py
xm.hitcounter.egg-info/PKG-INFO
xm.hitcounter.egg-info/SOURCES.txt
xm.hitcounter.egg-info/dependency_links.txt
xm.hitcounter.egg-info/entry_points.txt
xm.hitcounter.egg-info/namespace_packages.txt
xm.hitcounter.egg-info/not-zip-safe
xm.hitcounter.egg-info/requires.txt
xm.hitcounter.egg-info/top_level.txt
xm/hitcounter/__init__.py
xm/hitcounter/adapter.py
xm/hitcounter/catalog.py
xm/hitcounter/config.py
xm/hitcounter/configure.zcml
xm/hitcounter/core.py
xm/hitcounter/interfaces.py
xm/hitcounter/popularity_counter.py
xm/hitcounter/profiles.zcml
xm/hitcounter/setuphandlers.py
xm/hitcounter/tests.py
xm/hitcounter/tool.gif
xm/hitcounter/version.txt
xm/hitcounter/browser/__init__.py
xm/hitcounter/browser/configure.zcml
xm/hitcounter/browser/lsansd.ttf
xm/hitcounter/browser/mostpopular.py
xm/hitcounter/browser/object_hits.pt
xm/hitcounter/browser/object_hits.py
xm/hitcounter/content/__init__.py
xm/hitcounter/content/container.py
xm/hitcounter/doc/__init__.py
xm/hitcounter/doc/_xm.hitcounder.test.txt
xm/hitcounter/doc/stress.py
xm/hitcounter/doc/xm.hitcounter.txt
xm/hitcounter/profiles/default/catalog.xml
xm/hitcounter/profiles/default/import_steps.xml
xm/hitcounter/profiles/default/metadata.xml
xm/hitcounter/profiles/default/toolset.xml
xm/hitcounter/profiles/default/types.xml