Metadata-Version: 1.0
Name: xm.hitcounter
Version: 0.0.1
Summary: Easy and efficient plone hit counter
Home-page: http://svn.plone.org/svn/plone/plone.example
Author: Aiko Mastboom
Author-email: plone-developers@lists.sourceforge.net
License: GPL
Platform: UNKNOWN
Classifier: Framework :: Plone
Classifier: Programming Language :: Python
Classifier: Topic :: Software Development :: Libraries :: Python Modules
